src/square_mcp/__init__.py
src/square_mcp/__main__.py
src/square_mcp/server.py
mseep_square_mcp-0.2.2.dist-info/METADATA
mseep_square_mcp-0.2.2.dist-info/WHEEL
mseep_square_mcp-0.2.2.dist-info/entry_points.txt
mseep_square_mcp-0.2.2.dist-info/licenses/LICENSE
mseep_square_mcp-0.2.2.dist-info/RECORD
