Metadata-Version: 2.4
Name: mseep-square-mcp
Version: 0.2.2
Summary: Square API Model Context Protocol Server
Project-URL: Homepage, https://github.com/Kvadratni/square-mcp
Project-URL: Repository, https://github.com/Kvadratni/square-mcp
Project-URL: Documentation, https://github.com/Kvadratni/square-mcp#readme
Project-URL: Bug Tracker, https://github.com/Kvadratni/square-mcp/issues
Author-email: Max Novich <mnovich@block.xyz>
License-Expression: MIT
License-File: LICENSE
Keywords: api,mcp,payments,square
Classifier: Intended Audience :: Developers
Classifier: License :: OSI Approved :: MIT License
Classifier: Programming Language :: Python :: 3
Classifier: Programming Language :: Python :: 3.10
Classifier: Programming Language :: Python :: 3.11
Requires-Python: >=3.10
Requires-Dist: mcp[cli]>=1.2.0
Requires-Dist: squareup>=33.1.0
